LICENSE
hdc_bin_collection/__init__.py
hdc_bin_collection/hdc_bin_collection.py
hdc_bin_collection-1.0.0.dist-info/LICENSE
hdc_bin_collection-1.0.0.dist-info/METADATA
hdc_bin_collection-1.0.0.dist-info/WHEEL
hdc_bin_collection-1.0.0.dist-info/RECORD
