Metadata-Version: 2.1
Name: hdc-bin-collection
Version: 1.0.0
Summary: An async module that finds the next bin collection dates for a specific address in Market Harborough, UK. Uses the UPRN to find the address.
Home-page: https://github.com/caraar12345/hdc-bin-collection
License: MIT
Keywords: hdc,bin,collection,Market Harborough,Harborough,LE16,garbage,trash,rubbish,recycling
Author: Aaron Carson
Author-email: aaron@aaroncarson.co.uk
Requires-Python: >=3.9,<4.0
Classifier: License :: OSI Approved :: MIT License
Classifier: Programming Language :: Python :: 3
Classifier: Programming Language :: Python :: 3.9
Classifier: Programming Language :: Python :: 3.10
Classifier: Programming Language :: Python :: 3.11
Requires-Dist: aiohttp (>=3.8.1,<4.0.0)
Requires-Dist: asyncio (>=3.4.3,<4.0.0)
Requires-Dist: beautifulsoup4 (>=4.11.0,<5.0.0)
Requires-Dist: requests (>=2.27.1,<3.0.0)
